Workbook

Sheet Exchange_Economics
A1: INFERENCE EXCHANGE — LOCAL HARDWARE vs. CLOUD API ECONOMICS & SOR MATRIX
A2: Live parameterized unit economics, utilization break-even analysis, and Prefill/Decode Smart Order Routing (Oct 2026 AA v4.3.2)
A4: GLOBAL TCO & EXCHANGE CLEARING PARAMETERS (EDITABLE INPUTS)
A5: Hardware Amortization Horizon (Years) | B5: 3 | C5: Standard prosumer/cluster depreciation cycle
A6: Hardware Residual / Resale Value (%) | B6: 0.3 | C6: 36-month secondary market residual value (Apple/NVIDIA)
A7: California Commercial/Residential Power ($/kWh) | B7: 0.35 | C7: SDG&E / PG&E blended kWh rate
A8: Solo Developer Duty Cycle (Utilization %) | B8: 0.08 | C8: Single user local interactive coding (~1.9 hrs/day active)
A9: Inference Exchange Node Utilization (%) | B9: 0.65 | C9: Pooled liquidity node cleared via Inference Exchange SOR
A10: Exchange Prefix Cache Hit Rate (%) | B10: 0.8 | C10: Warm prefix cache hit ratio on multi-turn agentic loops
A12: 1. THE UTILIZATION PARADOX & CLOUD ARBITRAGE MATRIX (LIVE FORMULAS)
A13: Scenario ID | B13: Representative Workload / Tier | C13: Hardware System | D13: Local Model & Recipe | E13: AA Index (v4.3.2) | F13: Single Decode (tok/s) | G13: Batched Decode (tok/s) | H13: Solo Dev Cost ($/1M Out @ 8% Util) | I13: Exchange Node Cost ($/1M Out @ 65% Util) | J13: Cloud API Output Price ($/1M Out) | K13: Exchange Savings vs. Cloud API (%)
A14: ARB-01 | B14: Dense 27B Coding Workhorse (Apple Prosumer) | C14: =Experiments!F10 | D14: =Experiments!O10 | E14: =Experiments!AK10 | F14: =Experiments!Z10 | G14: =Experiments!AA10 | H14: =Experiments!AI10 | I14: =Experiments!AJ10 | J14: =Models!M13 | K14: =(J14-I14)/J14
A15: ARB-02 | B15: Dense 27B Lossless Q8 (Apple Studio Tier) | C15: =Experiments!F11 | D15: =Experiments!O11 | E15: =Experiments!AK11 | F15: =Experiments!Z11 | G15: =Experiments!AA11 | H15: =Experiments!AI11 | I15: =Experiments!AJ11 | J15: =Models!M13 | K15: =(J15-I15)/J15
A16: ARB-03 | B16: Dense 27B High-Batch Server (NVIDIA Tier) | C16: =Experiments!F12 | D16: =Experiments!O12 | E16: =Experiments!AK12 | F16: =Experiments!Z12 | G16: =Experiments!AA12 | H16: =Experiments!AI12 | I16: =Experiments!AJ12 | J16: =Models!M13 | K16: =(J16-I16)/J16
A17: ARB-04 | B17: 120B Fast MoE Workhorse (NVIDIA Prefill+Batch) | C17: =Experiments!F6 | D17: =Experiments!O6 | E17: =Experiments!AK6 | F17: =Experiments!Z6 | G17: =Experiments!AA6 | H17: =Experiments!AI6 | I17: =Experiments!AJ6 | J17: =Models!M12 | K17: =(J17-I17)/J17
A18: ARB-05 | B18: 320B Frontier Open MoE (Monolithic 256GB) | C18: =Experiments!F14 | D18: =Experiments!O14 | E18: =Experiments!AK14 | F18: =Experiments!Z14 | G18: =Experiments!AA14 | H18: =Experiments!AI14 | I18: =Experiments!AJ14 | J18: =Models!M8 | K18: =(J18-I18)/J18
A19: ARB-06 | B19: 235B Distributed MoE (2x Spark RoCEv2) | C19: =Experiments!F8 | D19: =Experiments!O8 | E19: =Experiments!AK8 | F19: =Experiments!Z8 | G19: =Experiments!AA8 | H19: =Experiments!AI8 | I19: =Experiments!AJ8 | J19: =Models!M10 | K19: =(J19-I19)/J19
A22: 2. SMART ORDER ROUTER (SOR) DISAGGREGATED HARDWARE SPECIALIZATION MATRIX
A23: Order Book Contract Type | B23: Primary Bottleneck | C23: Optimal Hardware Provider | D23: Target Engine & Quant | E23: Prefill Speed (tok/s) | F23: Decode Speed (tok/s) | G23: Why the Exchange Routes Here (Market Microstructure Rationale)
A24: LEG 1: Cold Long-Context Prefill (16k-64k RAG / Repo Ingest) | B24: Compute TFLOPS (FP4 Tensor Cores) | C24: NVIDIA DGX Spark 128GB ($4,699) | D24: vLLM + MXFP4 / NVFP4 | E24: 2053 | F24: 58.7 | G24: Blackwell ~1,000 FP4 TFLOPS crushes prompt prefill (2,053-2,442 tok/s), cutting TTFT by 2.5x-3x vs Apple Silicon.
A25: LEG 2: Warm Prefix-Cached Multi-Turn Agent Loop (ContainerClaw) | B25: Memory Bandwidth + Prefix Trie Hit | C25: Apple M5 Max 128GB ($5,399) | D25: vllm-mlx v0.4.2 + Q4/Q6 | E25: 1450 | F25: 135.2 | G25: 614 GB/s unified memory + zero-copy trie prefix cache bypasses prefill and streams 33-135 tok/s at 105W.
A26: LEG 3: Frontier 235B-320B MoE Low-Latency Interactive Decode | B26: Monolithic RAM Capacity + Bandwidth | C26: Apple M5 Ultra 256GB ($9,499) | D26: oMLX / vllm-mlx Q4 | E26: 980 | F26: 88 | G26: 1,200 GB/s unified memory holds 186GB 320B MoE in a single address space without 200GbE network TP latency.
A27: LEG 4: High-Concurrency Throughput Batch Clearing (c=8 to c=32) | B27: Continuous Batching + CUDAGraph | C27: NVIDIA DGX Spark 128GB ($4,699) | D27: vLLM + CUDAGraph (max 2048) | E27: 2442 | F27: 198.4 | G27: vLLM PagedAttention + CUDAGraph scales gpt-oss-120b to 198+ tok/s aggregate ($0.39/1M tokens @ 65% util).

Sheet Hardware
A1: HARDWARE CATALOG (DIMENSION TABLE — dim_hardware)
A2: Verified system specifications, memory bandwidth, TDP, CapEx, and live hourly TCO formulas referenced by Experiments
A4: hardware_id | B4: vendor | C4: system_name | D4: chip | E4: nodes | F4: memory_gb_per_node | G4: total_memory_gb | H4: memory_type | I4: memory_bandwidth_gbps_per_node | J4: aggregate_bandwidth_gbps | K4: fp4_or_int4_compute_note | L4: interconnect | M4: est_system_cost_usd | N4: typical_power_w | O4: hourly_tco_solo_8pct_usd | P4: hourly_tco_exchange_65pct_usd | Q4: notes
A5: HW-001 | B5: Apple | C5: MacBook Pro / Mac Studio M5 Max 128GB | D5: Apple M5 Max (18C CPU / 40C GPU) | E5: 1 | F5: 128 | G5: =E5*F5 | H5: Unified LPDDR5X | I5: 614 | J5: =E5*I5 | K5: Metal GPU + Neural Accelerators; MLX Q4/Q6/Q8 native | L5: Single-node Unified Memory | M5: 5399 | N5: 110 | O5: =(M5*(1-Exchange_Economics!$B$6))/(Exchange_Economics!$B$5*8760*Exchange_Economics!$B$8)+(N5/1000)*Exchange_Economics!$B$7 | P5: =(M5*(1-Exchange_Economics!$B$6))/(Exchange_Economics!$B$5*8760*Exchange_Economics!$B$9)+(N5/1000)*Exchange_Economics!$B$7 | Q5: Verified MBP/Studio M5 Max 128GB baseline (614 GB/s). Sweet spot for 8B-32B dense & 30B-120B MoE.
A6: HW-002 | B6: Apple | C6: Mac Studio M5 Ultra 256GB | D6: Apple M5 Ultra (36C CPU / 80C GPU) | E6: 1 | F6: 256 | G6: =E6*F6 | H6: Unified Memory | I6: 1200 | J6: =E6*I6 | K6: Dual-die UltraFusion; high memory bandwidth decode specialist | L6: Single-node Unified Memory | M6: 9499 | N6: 185 | O6: =(M6*(1-Exchange_Economics!$B$6))/(Exchange_Economics!$B$5*8760*Exchange_Economics!$B$8)+(N6/1000)*Exchange_Economics!$B$7 | P6: =(M6*(1-Exchange_Economics!$B$6))/(Exchange_Economics!$B$5*8760*Exchange_Economics!$B$9)+(N6/1000)*Exchange_Economics!$B$7 | Q6: Monolithic 256GB address space at 1.2 TB/s. Ideal for 120B-320B 4-bit MoE decode without network TP overhead.
A7: HW-003 | B7: Apple | C7: Mac Studio M5 Ultra 512GB (Late Oct 2026) | D7: Apple M5 Ultra (36C CPU / 80C GPU) | E7: 1 | F7: 512 | G7: =E7*F7 | H7: Unified Memory | I7: 1200 | J7: =E7*I7 | K7: High-capacity unified memory node; shipping late Oct 2026 (est. CapEx) | L7: Single-node Unified Memory | M7: 13499 | N7: 215 | O7: =(M7*(1-Exchange_Economics!$B$6))/(Exchange_Economics!$B$5*8760*Exchange_Economics!$B$8)+(N7/1000)*Exchange_Economics!$B$7 | P7: =(M7*(1-Exchange_Economics!$B$6))/(Exchange_Economics!$B$5*8760*Exchange_Economics!$B$9)+(N7/1000)*Exchange_Economics!$B$7 | Q7: Analytical projection only until retail units ship. Targets 400B-685B Q4 MoE resident weights.
A8: HW-004 | B8: NVIDIA | C8: DGX Spark 128GB (Single Node) | D8: NVIDIA GB10 Grace Blackwell Superchip (SM121) | E8: 1 | F8: 128 | G8: =E8*F8 | H8: Coherent Unified LPDDR5x | I8: 273 | J8: =E8*I8 | K8: ~1,000 TOPS/TFLOPS FP4 Blackwell Tensor Cores | L8: Single-node NVLink-C2C | M8: 4699 | N8: 125 | O8: =(M8*(1-Exchange_Economics!$B$6))/(Exchange_Economics!$B$5*8760*Exchange_Economics!$B$8)+(N8/1000)*Exchange_Economics!$B$7 | P8: =(M8*(1-Exchange_Economics!$B$6))/(Exchange_Economics!$B$5*8760*Exchange_Economics!$B$9)+(N8/1000)*Exchange_Economics!$B$7 | Q8: Compute-heavy prefill monster (~2,000+ tok/s prefill) & high-batch server, but decode-limited by 273 GB/s bandwidth.
A9: HW-005 | B9: NVIDIA | C9: 2x DGX Spark 256GB Cluster | D9: 2x NVIDIA GB10 Grace Blackwell (SM121) | E9: 2 | F9: 128 | G9: =E9*F9 | H9: Distributed Unified LPDDR5x (2x128GB) | I9: 273 | J9: =E9*I9 | K9: ~2,000 TOPS/TFLOPS FP4 aggregate across 2 nodes | L9: ConnectX-7 200GbE QSFP112 RoCEv2 (~1.2us) | M9: 9398 | N9: 250 | O9: =(M9*(1-Exchange_Economics!$B$6))/(Exchange_Economics!$B$5*8760*Exchange_Economics!$B$8)+(N9/1000)*Exchange_Economics!$B$7 | P9: =(M9*(1-Exchange_Economics!$B$6))/(Exchange_Economics!$B$5*8760*Exchange_Economics!$B$9)+(N9/1000)*Exchange_Economics!$B$7 | Q9: Distributed 256GB via TP=2/EP=2 over 200GbE. Enables 235B+ MoE models that exceed single 128GB node.

Sheet Models
A1: MODELS CATALOG & ARTIFICIAL ANALYSIS v4.3.2 BASELINES (dim_models)
A2: Verified October 2026 Artificial Analysis Intelligence Index (v4.3.2), active vs. resident parameters, and cloud API pricing
A4: model_id | B4: model_name | C4: provider_or_org | D4: license_type | E4: architecture | F4: total_params_b | G4: active_params_b | H4: resident_params_b | I4: aa_intelligence_index | J4: aa_coding_index | K4: aa_speed_output_tps | L4: aa_input_usd_per_m | M4: aa_output_usd_per_m | N4: aa_price_blended_usd_per_m | O4: aa_cost_per_task_usd | P4: recommended_local_fit | Q4: notes
A5: MOD-001 | B5: Claude Opus 5.5 (Max) | C5: Anthropic | D5: Proprietary API | E5: Proprietary Frontier Reasoning | F5: 0 | G5: 0 | H5: 0 | I5: 58 | J5: 55.4 | K5: 95 | L5: 4 | M5: 20 | N5: =(3*L5+M5)/4 | O5: 5.98 | P5: Cloud API Reference Only | Q5: AA v4.3.2 #1 overall intelligence ceiling (58). $4/$20 per 1M tokens ($8.00 3:1 blended).
A6: MOD-002 | B6: GPT-6.1 Sol (xhigh) | C6: OpenAI | D6: Proprietary API | E6: Proprietary Frontier Reasoning | F6: 0 | G6: 0 | H6: 0 | I6: 50 | J6: 45.7 | K6: 72 | L6: 2.5 | M6: 15 | N6: =(3*L6+M6)/4 | O6: 1.65 | P6: Cloud API Reference Only | Q6: AA v4.3.2 OpenAI flagship reference. High token efficiency on reasoning tasks.
A7: MOD-003 | B7: Gemini 3.8 Flash | C7: Google | D7: Proprietary API | E7: Proprietary Fast Frontier | F7: 0 | G7: 0 | H7: 0 | I7: 40 | J7: 40 | K7: 215 | L7: 0.15 | M7: 0.6 | N7: =(3*L7+M7)/4 | O7: 0.22 | P7: Cloud API Speed/Cost Baseline | Q7: Primary high-speed proprietary Flash baseline that local inference must beat on cost or privacy.
A8: MOD-004 | B8: GLM-5.3-Flash | C8: Zhipu AI (Z.ai) | D8: Open Weights (MIT) | E8: MoE (Hybrid Sparse + Linear Attention) | F8: 320 | G8: 18 | H8: 320 | I8: 42 | J8: 41.2 | K8: 67 | L8: 0.15 | M8: 0.5 | N8: =(3*L8+M8)/4 | O8: 0.28 | P8: M5 Ultra 256GB (Q4) / 2x DGX Spark 256GB (INT4) | Q8: AA v4.3.2 Score 42. 320B total / 18B active (~168GB in Q4). Cannot fit resident in 128GB without NVMe paging.
A9: MOD-005 | B9: DeepSeek-V4.1-Flash | C9: DeepSeek | D9: Open Weights (MIT) | E9: Causal Encoder-Decoder MoE + 196B Engram | F9: 748 | G9: 16 | H9: 552 | I9: 39 | J9: 38.5 | K9: 190 | L9: 0.044 | M9: 0.765 | N9: =(3*L9+M9)/4 | O9: 0.27 | P9: M5 Ultra 512GB (Q4) or M5 Ultra 256GB (Q2/Q3 + NVMe Engram) | Q9: AA v4.3.2 Score 39. 552B MoE backbone (8B prefill / 16B decode active) + 196B Engram table on NVMe.
A10: MOD-006 | B10: Qwen3-235B-A22B-Instruct | C10: Alibaba Qwen | D10: Open Weights (Apache-2.0) | E10: MoE | F10: 235 | G10: 22 | H10: 235 | I10: 37 | J10: 35.8 | K10: 62 | L10: 0.2 | M10: 0.8 | N10: =(3*L10+M10)/4 | O10: 0.44 | P10: M5 Ultra 256GB (Q4) / 2x DGX Spark 256GB (GPTQ-Marlin) | Q10: Verified on 2x DGX Spark by Conselara Labs (17.0 tok/s single, 36.4 tok/s at b=4) and M5 Ultra 256GB.
A11: MOD-007 | B11: Qwen3.5-122B-A10B | C11: Alibaba Qwen | D11: Open Weights (Apache-2.0) | E11: MoE | F11: 122 | G11: 10 | H11: 122 | I11: 35.5 | J11: 34.9 | K11: 88 | L11: 0.18 | M11: 0.65 | N11: =(3*L11+M11)/4 | O11: 0.36 | P11: M5 Max 128GB / DGX Spark 128GB / M5 Ultra 256GB | Q11: 122B total / 10B active (~65GB in Q4). Fits comfortably on single 128GB node with 10B active decode speed.
A12: MOD-008 | B12: gpt-oss-120b | C12: OpenAI | D12: Open Weights (Apache-2.0) | E12: MoE | F12: 117 | G12: 5.1 | H12: 117 | I12: 33 | J12: 32.5 | K12: 145 | L12: 0.1 | M12: 0.4 | N12: =(3*L12+M12)/4 | O12: 0.25 | P12: DGX Spark 128GB (MXFP4) / M5 Max 128GB (MLX Q4) | Q12: 117B total / 5.1B active (~61GB MXFP4). Verified 58.7 tok/s decode & 2,053 tok/s prefill on single DGX Spark.
A13: MOD-009 | B13: Qwen3.8-27B (xhigh) | C13: Alibaba Qwen | D13: Open Weights (Apache-2.0) | E13: Dense | F13: 27 | G13: 27 | H13: 27 | I13: 34 | J13: 33.8 | K13: 45 | L13: 0.5 | M13: 3 | N13: =(3*L13+M13)/4 | O13: 1.01 | P13: M5 Max 128GB / M5 Ultra 256GB / DGX Spark 128GB | Q13: AA v4.3.2 #1 small open-weight model (34). Cloud API charges $3.00/1M out ($1.01/task)—prime local arbitrage target.
A14: MOD-010 | B14: GLM-4.7-Flash-30B-A3B | C14: Zhipu AI (Z.ai) | D14: Open Weights (MIT) | E14: MoE | F14: 30 | G14: 3 | H14: 30 | I14: 29.5 | J14: 28.9 | K14: 160 | L14: 0.07 | M14: 0.25 | N14: =(3*L14+M14)/4 | O14: 0.14 | P14: M5 Max 128GB / DGX Spark 128GB | Q14: 30B total / 3B active (~16.5GB Q4, ~24GB Q6). Ultra-fast local agentic sub-router model (>110 tok/s on M5 Max).
A15: MOD-011 | B15: Qwen3-8B | C15: Alibaba Qwen | D15: Open Weights (Apache-2.0) | E15: Dense | F15: 8.2 | G15: 8.2 | H15: 8.2 | I15: 24 | J15: 23.1 | K15: 140 | L15: 0.05 | M15: 0.15 | N15: =(3*L15+M15)/4 | O15: 0.07 | P15: M5 Max 128GB / DGX Spark 128GB | Q15: Verified in vllm-mlx #637 on M5 Max 128GB across concurrency c=1 to c=15.

Sheet Recipes
A1: REPRODUCIBLE EXECUTION RECIPES (dim_recipes)
A2: Verified CLI launch configurations, quantization bit-widths, KV cache modes, and concurrency sweet spots
A4: recipe_id | B4: hardware_id | C4: system_name | D4: model_name | E4: total_params_b | F4: quantization | G4: quant_bits | H4: engine | I4: launch_or_runtime_recipe | J4: context_target | K4: kv_cache_mode | L4: speculative_decoding | M4: concurrency_sweet_spot | N4: expected_prefill_tps | O4: expected_decode_tps_single | P4: expected_decode_tps_batched | Q4: memory_footprint_gb | R4: stability_rating | S4: source_url | T4: notes
A5: REC-001 | B5: HW-004 | C5: =INDEX(Hardware!$C$5:$C$9, MATCH(B5, Hardware!$A$5:$A$9, 0)) | D5: gpt-oss-120b | E5: =INDEX(Models!$F$5:$F$15, MATCH(D5, Models!$B$5:$B$15, 0)) | F5: MXFP4 | G5: 4.25 | H5: vLLM (Container 26.01+) | I5: vllm serve openai/gpt-oss-120b --quantization mxfp4 --gpu-memory-utilization 0.90 --max-cudagraph-capture-size 2048 --enable-prefix-caching | J5: 32768 | K5: FP8 | L5: None | M5: 1-16 | N5: 2053 | O5: 58.7 | P5: 198 | Q5: 68.4 | R5: Production (Verified) | S5: https://conselara.dev/notes/dgx-spark-benchmarks/ | T5: Conselara Labs verified single-node DGX Spark benchmark: 2,053 tok/s prefill (2k prompt) & 57.5-60.0 tok/s pure decode.
A6: REC-002 | B6: HW-005 | C6: =INDEX(Hardware!$C$5:$C$9, MATCH(B6, Hardware!$A$5:$A$9, 0)) | D6: Qwen3-235B-A22B-Instruct | E6: =INDEX(Models!$F$5:$F$15, MATCH(D6, Models!$B$5:$B$15, 0)) | F6: GPTQ-Int4 (Marlin) | G6: 4 | H6: vLLM (Ray TP=2, EP=2) | I6: vllm serve Qwen/Qwen3-235B-A22B-GPTQ-Int4 --quantization gptq_marlin --tensor-parallel-size 2 --enable-expert-parallel --gpu-memory-utilization 0.85 | J6: 32768 | K6: FP8 | L6: None | M6: 1-4 | N6: 920 | O6: 17 | P6: 36.4 | Q6: 148 | R6: Production (Verified) | S6: https://conselara.dev/notes/dgx-spark-benchmarks/ | T6: Verified by Conselara Labs on 2x DGX Spark over 200GbE QSFP112. Note: gptq_marlin (17.0 tok/s) beats NVFP4 (11.73 tok/s) on SM121.
A7: REC-003 | B7: HW-001 | C7: =INDEX(Hardware!$C$5:$C$9, MATCH(B7, Hardware!$A$5:$A$9, 0)) | D7: Qwen3-8B | E7: =INDEX(Models!$F$5:$F$15, MATCH(D7, Models!$B$5:$B$15, 0)) | F7: MLX-4bit | G7: 4.5 | H7: vllm-mlx v0.4.0 | I7: vllm-mlx serve mlx-community/Qwen3-8B-4bit --continuous-batching --max-num-seqs 16 --enable-prefix-caching | J7: 16384 | K7: FP16 | L7: None | M7: 4-8 | N7: 1450 | O7: 98.5 | P7: 285 | Q7: 14.2 | R7: Production (Verified) | S7: https://github.com/waybarrios/vllm-mlx/discussions/637 | T7: Actual benchmark from vllm-mlx Discussion #637 on M5 Max 128GB: IELTS scoring workload across concurrency c=1 to c=15.
A8: REC-004 | B8: HW-001 | C8: =INDEX(Hardware!$C$5:$C$9, MATCH(B8, Hardware!$A$5:$A$9, 0)) | D8: Qwen3.8-27B (xhigh) | E8: =INDEX(Models!$F$5:$F$15, MATCH(D8, Models!$B$5:$B$15, 0)) | F8: MLX-4bit | G8: 4.5 | H8: vllm-mlx v0.4.2 | I8: vllm-mlx serve mlx-community/Qwen3.8-27B-4bit --continuous-batching --kv-bits 8 --enable-prefix-caching | J8: 32768 | K8: Q8 | L8: None | M8: 2-4 | N8: 740 | O8: 33.5 | P8: 78 | Q8: 19.8 | R8: Production | S8: https://github.com/waybarrios/vllm-mlx | T8: 27B dense model in 4.5-bit (~15.2GB weights + 4.6GB KV cache). 614 GB/s roofline = 40.4 tok/s; achieves 33.5 tok/s (83% eff).
A9: REC-005 | B9: HW-002 | C9: =INDEX(Hardware!$C$5:$C$9, MATCH(B9, Hardware!$A$5:$A$9, 0)) | D9: Qwen3.8-27B (xhigh) | E9: =INDEX(Models!$F$5:$F$15, MATCH(D9, Models!$B$5:$B$15, 0)) | F9: MLX-8bit | G9: 8 | H9: vllm-mlx v0.4.2 | I9: vllm-mlx serve mlx-community/Qwen3.8-27B-8bit --continuous-batching --kv-bits 8 --enable-prefix-caching | J9: 65536 | K9: Q8 | L9: None | M9: 4-8 | N9: 1180 | O9: 36.2 | P9: 96 | Q9: 36.5 | R9: Production | S9: https://github.com/waybarrios/vllm-mlx | T9: Near-lossless 8-bit dense 27B on M5 Ultra (1,200 GB/s / 27 GB = 44.4 tok/s roofline; 36.2 tok/s = 81.5% bandwidth efficiency).
A10: REC-006 | B10: HW-002 | C10: =INDEX(Hardware!$C$5:$C$9, MATCH(B10, Hardware!$A$5:$A$9, 0)) | D10: GLM-5.3-Flash | E10: =INDEX(Models!$F$5:$F$15, MATCH(D10, Models!$B$5:$B$15, 0)) | F10: MLX-4bit | G10: 4.25 | H10: oMLX v0.22.0 | I10: omlx serve zai-org/GLM-5.3-Flash-4bit --kv-quant q8 --tiered-ssd-cache /tmp/omlx_cache --max-batch-size 8 | J10: 65536 | K10: Q8 + Tiered SSD Prefix | L10: None | M10: 2-6 | N10: 980 | O10: 88 | P10: 195 | Q10: 186 | R10: Experimental / Roofline Model | S10: https://github.com/jundot/omlx | T10: 320B total params in 4.25-bit requires ~170GB weights + 16GB KV = 186GB (fits in 256GB M5 Ultra, NOT 128GB). 18B active -> 125 tok/s roofline.
A11: REC-007 | B11: HW-001 | C11: =INDEX(Hardware!$C$5:$C$9, MATCH(B11, Hardware!$A$5:$A$9, 0)) | D11: GLM-4.7-Flash-30B-A3B | E11: =INDEX(Models!$F$5:$F$15, MATCH(D11, Models!$B$5:$B$15, 0)) | F11: MLX-6bit | G11: 6 | H11: vllm-mlx v0.4.2 | I11: vllm-mlx serve mlx-community/GLM-4.7-Flash-30B-A3B-6bit --continuous-batching --enable-prefix-caching | J11: 32768 | K11: Q8 | L11: None | M11: 4-8 | N11: 1650 | O11: 135.2 | P11: 310 | Q11: 28.5 | R11: Production | S11: https://github.com/waybarrios/vllm-mlx | T11: Reconciles old EXP-006 row: 28.5GB footprint in 6-bit is physically GLM-4.7-Flash-30B-A3B (22.5GB weights + 6GB KV), NOT 320B GLM-5.3.
A12: REC-008 | B12: HW-002 | C12: =INDEX(Hardware!$C$5:$C$9, MATCH(B12, Hardware!$A$5:$A$9, 0)) | D12: DeepSeek-V4.1-Flash | E12: =INDEX(Models!$F$5:$F$15, MATCH(D12, Models!$B$5:$B$15, 0)) | F12: Dynamic-Q2.7 + NVMe Engram | G12: 2.75 | H12: oMLX v0.22.0 | I12: omlx serve deepseek-ai/DeepSeek-V4.1-Flash-UD-Q2_K_XL --engram-offload nvme --kv-quant q4 --enable-mtp | J12: 65536 | K12: Q4 + NVMe Engram Table | L12: MTP (Multi-Token Prediction) | M12: 1-4 | N12: 840 | O12: 48.2 | P12: 115 | Q12: 212 | R12: Experimental / Roofline Model | S12: https://huggingface.co/deepseek-ai | T12: 552B MoE backbone quantized to 2.75-bit (~190GB RAM) + 196B Engram lookup streamed from NVMe SSD (~22GB active cache).

Sheet Experiments
A1: EXPERIMENTS FACT TABLE (fact_experiments) — RELATIONAL LOOKUPS + AUTOMATED PHYSICS GATES
A2: Blue headers indicate live formula columns dynamically joined from Hardware & Models or computed via Roofline/TCO equations
A4: experiment_id | B4: date | C4: evidence_tier | D4: hardware_id | E4: platform | F4: chip_or_system | G4: nodes | H4: memory_gb_per_node | I4: total_memory_gb | J4: memory_bandwidth_gbps | K4: interconnect | L4: system_cost_usd | M4: power_watts | N4: engine_and_version | O4: model_name | P4: provider_or_org | Q4: architecture | R4: total_params_b | S4: active_params_b | T4: resident_params_b | U4: quantization | V4: quant_bits | W4: offload_mode | X4: concurrency | Y4: prefill_tps | Z4: decode_tps_single | AA4: decode_tps_agg | AB4: ttft_ms | AC4: peak_memory_gb | AD4: tokens_per_watt | AE4: min_weight_ram_gb | AF4: theoretical_roofline_tps | AG4: bandwidth_efficiency_pct | AH4: physics_gate_status | AI4: cost_solo_8pct_usd_per_m | AJ4: cost_exchange_65pct_usd_per_m | AK4: aa_intelligence_index | AL4: cloud_api_output_usd_per_m | AM4: exchange_vs_cloud_Arbitrage_pct | AN4: source_url_or_note
A5: EXP-001 | B5: 2026-10-10 | C5: TIER_2_EXTERNAL_VERIFIED | D5: HW-004 | E5: =INDEX(Hardware!$B$5:$B$9, MATCH(D5, Hardware!$A$5:$A$9, 0)) | F5: =INDEX(Hardware!$C$5:$C$9, MATCH(D5, Hardware!$A$5:$A$9, 0)) | G5: =INDEX(Hardware!$E$5:$E$9, MATCH(D5, Hardware!$A$5:$A$9, 0)) | H5: =INDEX(Hardware!$F$5:$F$9, MATCH(D5, Hardware!$A$5:$A$9, 0)) | I5: =INDEX(Hardware!$G$5:$G$9, MATCH(D5, Hardware!$A$5:$A$9, 0)) | J5: =INDEX(Hardware!$J$5:$J$9, MATCH(D5, Hardware!$A$5:$A$9, 0)) | K5: =INDEX(Hardware!$L$5:$L$9, MATCH(D5, Hardware!$A$5:$A$9, 0)) | L5: =INDEX(Hardware!$M$5:$M$9, MATCH(D5, Hardware!$A$5:$A$9, 0)) | M5: 125 | N5: vLLM (26.01-py3) | O5: gpt-oss-120b | P5: =INDEX(Models!$C$5:$C$15, MATCH(O5, Models!$B$5:$B$15, 0)) | Q5: =INDEX(Models!$E$5:$E$15, MATCH(O5, Models!$B$5:$B$15, 0)) | R5: =INDEX(Models!$F$5:$F$15, MATCH(O5, Models!$B$5:$B$15, 0)) | S5: =INDEX(Models!$G$5:$G$15, MATCH(O5, Models!$B$5:$B$15, 0)) | T5: =INDEX(Models!$H$5:$H$15, MATCH(O5, Models!$B$5:$B$15, 0)) | U5: MXFP4 | V5: 4.25 | W5: resident | X5: 1 | Y5: 2053 | Z5: 58.7 | AA5: 58.7 | AB5: 998 | AC5: 68.4 | AD5: =AA5/M5 | AE5: =T5*(V5/8)*1.05 | AF5: =J5/(S5*(V5/8)) | AG5: =Z5/AF5 | AH5: =IF(AC5>I5,"FAIL:_EXCEEDS_NODE_RAM",IF(AND(W5="resident",AC5<AE5),"FAIL:_WEIGHTS_EXCEED_PEAK_RAM",IF(AG5>1.05,"FAIL:_EXCEEDS_ROOFLINE","PASS"))) | AI5: =((L5*(1-Exchange_Economics!$B$6))/(Exchange_Economics!$B$5*8760*Exchange_Economics!$B$8)+(M5/1000)*Exchange_Economics!$B$7)/(Z5*3600)*1000000 | AJ5: =((L5*(1-Exchange_Economics!$B$6))/(Exchange_Economics!$B$5*8760*Exchange_Economics!$B$9)+(M5/1000)*Exchange_Economics!$B$7)/(AA5*3600)*1000000 | AK5: =INDEX(Models!$I$5:$I$15, MATCH(O5, Models!$B$5:$B$15, 0)) | AL5: =INDEX(Models!$M$5:$M$15, MATCH(O5, Models!$B$5:$B$15, 0)) | AM5: =(AL5-AJ5)/AL5 | AN5: https://conselara.dev/notes/dgx-spark-benchmarks/ (Verified single DGX Spark: 2,053 tok/s prefill, 57.5-60.0 tok/s decode)
A6: EXP-002 | B6: 2026-10-10 | C6: TIER_2_EXTERNAL_VERIFIED | D6: HW-004 | E6: =INDEX(Hardware!$B$5:$B$9, MATCH(D6, Hardware!$A$5:$A$9, 0)) | F6: =INDEX(Hardware!$C$5:$C$9, MATCH(D6, Hardware!$A$5:$A$9, 0)) | G6: =INDEX(Hardware!$E$5:$E$9, MATCH(D6, Hardware!$A$5:$A$9, 0)) | H6: =INDEX(Hardware!$F$5:$F$9, MATCH(D6, Hardware!$A$5:$A$9, 0)) | I6: =INDEX(Hardware!$G$5:$G$9, MATCH(D6, Hardware!$A$5:$A$9, 0)) | J6: =INDEX(Hardware!$J$5:$J$9, MATCH(D6, Hardware!$A$5:$A$9, 0)) | K6: =INDEX(Hardware!$L$5:$L$9, MATCH(D6, Hardware!$A$5:$A$9, 0)) | L6: =INDEX(Hardware!$M$5:$M$9, MATCH(D6, Hardware!$A$5:$A$9, 0)) | M6: 138 | N6: vLLM (26.01-py3) | O6: gpt-oss-120b | P6: =INDEX(Models!$C$5:$C$15, MATCH(O6, Models!$B$5:$B$15, 0)) | Q6: =INDEX(Models!$E$5:$E$15, MATCH(O6, Models!$B$5:$B$15, 0)) | R6: =INDEX(Models!$F$5:$F$15, MATCH(O6, Models!$B$5:$B$15, 0)) | S6: =INDEX(Models!$G$5:$G$15, MATCH(O6, Models!$B$5:$B$15, 0)) | T6: =INDEX(Models!$H$5:$H$15, MATCH(O6, Models!$B$5:$B$15, 0)) | U6: MXFP4 | V6: 4.25 | W6: resident | X6: 8 | Y6: 2442 | Z6: 24.8 | AA6: 198.4 | AB6: 1420 | AC6: 84.2 | AD6: =AA6/M6 | AE6: =T6*(V6/8)*1.05 | AF6: =J6/(S6*(V6/8)) | AG6: =Z6/AF6 | AH6: =IF(AC6>I6,"FAIL:_EXCEEDS_NODE_RAM",IF(AND(W6="resident",AC6<AE6),"FAIL:_WEIGHTS_EXCEED_PEAK_RAM",IF(AG6>1.05,"FAIL:_EXCEEDS_ROOFLINE","PASS"))) | AI6: =((L6*(1-Exchange_Economics!$B$6))/(Exchange_Economics!$B$5*8760*Exchange_Economics!$B$8)+(M6/1000)*Exchange_Economics!$B$7)/(Z6*3600)*1000000 | AJ6: =((L6*(1-Exchange_Economics!$B$6))/(Exchange_Economics!$B$5*8760*Exchange_Economics!$B$9)+(M6/1000)*Exchange_Economics!$B$7)/(AA6*3600)*1000000 | AK6: =INDEX(Models!$I$5:$I$15, MATCH(O6, Models!$B$5:$B$15, 0)) | AL6: =INDEX(Models!$M$5:$M$15, MATCH(O6, Models!$B$5:$B$15, 0)) | AM6: =(AL6-AJ6)/AL6 | AN6: https://conselara.dev/notes/dgx-spark-benchmarks/ (Batched c=8 run on single DGX Spark with CUDAGraph)
A7: EXP-003 | B7: 2026-10-10 | C7: TIER_2_EXTERNAL_VERIFIED | D7: HW-005 | E7: =INDEX(Hardware!$B$5:$B$9, MATCH(D7, Hardware!$A$5:$A$9, 0)) | F7: =INDEX(Hardware!$C$5:$C$9, MATCH(D7, Hardware!$A$5:$A$9, 0)) | G7: =INDEX(Hardware!$E$5:$E$9, MATCH(D7, Hardware!$A$5:$A$9, 0)) | H7: =INDEX(Hardware!$F$5:$F$9, MATCH(D7, Hardware!$A$5:$A$9, 0)) | I7: =INDEX(Hardware!$G$5:$G$9, MATCH(D7, Hardware!$A$5:$A$9, 0)) | J7: =INDEX(Hardware!$J$5:$J$9, MATCH(D7, Hardware!$A$5:$A$9, 0)) | K7: =INDEX(Hardware!$L$5:$L$9, MATCH(D7, Hardware!$A$5:$A$9, 0)) | L7: =INDEX(Hardware!$M$5:$M$9, MATCH(D7, Hardware!$A$5:$A$9, 0)) | M7: 235 | N7: vLLM (Ray TP=2, EP=2) (0.14.0) | O7: Qwen3-235B-A22B-Instruct | P7: =INDEX(Models!$C$5:$C$15, MATCH(O7, Models!$B$5:$B$15, 0)) | Q7: =INDEX(Models!$E$5:$E$15, MATCH(O7, Models!$B$5:$B$15, 0)) | R7: =INDEX(Models!$F$5:$F$15, MATCH(O7, Models!$B$5:$B$15, 0)) | S7: =INDEX(Models!$G$5:$G$15, MATCH(O7, Models!$B$5:$B$15, 0)) | T7: =INDEX(Models!$H$5:$H$15, MATCH(O7, Models!$B$5:$B$15, 0)) | U7: GPTQ-Int4 (Marlin) | V7: 4 | W7: resident | X7: 1 | Y7: 920 | Z7: 17 | AA7: 17 | AB7: 2225 | AC7: 142 | AD7: =AA7/M7 | AE7: =T7*(V7/8)*1.05 | AF7: =J7/(S7*(V7/8)) | AG7: =Z7/AF7 | AH7: =IF(AC7>I7,"FAIL:_EXCEEDS_NODE_RAM",IF(AND(W7="resident",AC7<AE7),"FAIL:_WEIGHTS_EXCEED_PEAK_RAM",IF(AG7>1.05,"FAIL:_EXCEEDS_ROOFLINE","PASS"))) | AI7: =((L7*(1-Exchange_Economics!$B$6))/(Exchange_Economics!$B$5*8760*Exchange_Economics!$B$8)+(M7/1000)*Exchange_Economics!$B$7)/(Z7*3600)*1000000 | AJ7: =((L7*(1-Exchange_Economics!$B$6))/(Exchange_Economics!$B$5*8760*Exchange_Economics!$B$9)+(M7/1000)*Exchange_Economics!$B$7)/(AA7*3600)*1000000 | AK7: =INDEX(Models!$I$5:$I$15, MATCH(O7, Models!$B$5:$B$15, 0)) | AL7: =INDEX(Models!$M$5:$M$15, MATCH(O7, Models!$B$5:$B$15, 0)) | AM7: =(AL7-AJ7)/AL7 | AN7: https://conselara.dev/notes/dgx-spark-benchmarks/ (Verified 2x DGX Spark 256GB: 17.0 tok/s single-stream via gptq_marlin)
A8: EXP-004 | B8: 2026-10-10 | C8: TIER_2_EXTERNAL_VERIFIED | D8: HW-005 | E8: =INDEX(Hardware!$B$5:$B$9, MATCH(D8, Hardware!$A$5:$A$9, 0)) | F8: =INDEX(Hardware!$C$5:$C$9, MATCH(D8, Hardware!$A$5:$A$9, 0)) | G8: =INDEX(Hardware!$E$5:$E$9, MATCH(D8, Hardware!$A$5:$A$9, 0)) | H8: =INDEX(Hardware!$F$5:$F$9, MATCH(D8, Hardware!$A$5:$A$9, 0)) | I8: =INDEX(Hardware!$G$5:$G$9, MATCH(D8, Hardware!$A$5:$A$9, 0)) | J8: =INDEX(Hardware!$J$5:$J$9, MATCH(D8, Hardware!$A$5:$A$9, 0)) | K8: =INDEX(Hardware!$L$5:$L$9, MATCH(D8, Hardware!$A$5:$A$9, 0)) | L8: =INDEX(Hardware!$M$5:$M$9, MATCH(D8, Hardware!$A$5:$A$9, 0)) | M8: 250 | N8: vLLM (Ray TP=2, EP=2) (0.14.0) | O8: Qwen3-235B-A22B-Instruct | P8: =INDEX(Models!$C$5:$C$15, MATCH(O8, Models!$B$5:$B$15, 0)) | Q8: =INDEX(Models!$E$5:$E$15, MATCH(O8, Models!$B$5:$B$15, 0)) | R8: =INDEX(Models!$F$5:$F$15, MATCH(O8, Models!$B$5:$B$15, 0)) | S8: =INDEX(Models!$G$5:$G$15, MATCH(O8, Models!$B$5:$B$15, 0)) | T8: =INDEX(Models!$H$5:$H$15, MATCH(O8, Models!$B$5:$B$15, 0)) | U8: GPTQ-Int4 (Marlin) | V8: 4 | W8: resident | X8: 4 | Y8: 1150 | Z8: 9.1 | AA8: 36.4 | AB8: 2890 | AC8: 154 | AD8: =AA8/M8 | AE8: =T8*(V8/8)*1.05 | AF8: =J8/(S8*(V8/8)) | AG8: =Z8/AF8 | AH8: =IF(AC8>I8,"FAIL:_EXCEEDS_NODE_RAM",IF(AND(W8="resident",AC8<AE8),"FAIL:_WEIGHTS_EXCEED_PEAK_RAM",IF(AG8>1.05,"FAIL:_EXCEEDS_ROOFLINE","PASS"))) | AI8: =((L8*(1-Exchange_Economics!$B$6))/(Exchange_Economics!$B$5*8760*Exchange_Economics!$B$8)+(M8/1000)*Exchange_Economics!$B$7)/(Z8*3600)*1000000 | AJ8: =((L8*(1-Exchange_Economics!$B$6))/(Exchange_Economics!$B$5*8760*Exchange_Economics!$B$9)+(M8/1000)*Exchange_Economics!$B$7)/(AA8*3600)*1000000 | AK8: =INDEX(Models!$I$5:$I$15, MATCH(O8, Models!$B$5:$B$15, 0)) | AL8: =INDEX(Models!$M$5:$M$15, MATCH(O8, Models!$B$5:$B$15, 0)) | AM8: =(AL8-AJ8)/AL8 | AN8: https://conselara.dev/notes/dgx-spark-benchmarks/ (Verified 2x DGX Spark 256GB: 36.4 tok/s aggregate at batch=4)
A9: EXP-005 | B9: 2026-10-08 | C9: TIER_2_EXTERNAL_VERIFIED | D9: HW-001 | E9: =INDEX(Hardware!$B$5:$B$9, MATCH(D9, Hardware!$A$5:$A$9, 0)) | F9: =INDEX(Hardware!$C$5:$C$9, MATCH(D9, Hardware!$A$5:$A$9, 0)) | G9: =INDEX(Hardware!$E$5:$E$9, MATCH(D9, Hardware!$A$5:$A$9, 0)) | H9: =INDEX(Hardware!$F$5:$F$9, MATCH(D9, Hardware!$A$5:$A$9, 0)) | I9: =INDEX(Hardware!$G$5:$G$9, MATCH(D9, Hardware!$A$5:$A$9, 0)) | J9: =INDEX(Hardware!$J$5:$J$9, MATCH(D9, Hardware!$A$5:$A$9, 0)) | K9: =INDEX(Hardware!$L$5:$L$9, MATCH(D9, Hardware!$A$5:$A$9, 0)) | L9: =INDEX(Hardware!$M$5:$M$9, MATCH(D9, Hardware!$A$5:$A$9, 0)) | M9: 95 | N9: vllm-mlx (v0.4.0) | O9: Qwen3-8B | P9: =INDEX(Models!$C$5:$C$15, MATCH(O9, Models!$B$5:$B$15, 0)) | Q9: =INDEX(Models!$E$5:$E$15, MATCH(O9, Models!$B$5:$B$15, 0)) | R9: =INDEX(Models!$F$5:$F$15, MATCH(O9, Models!$B$5:$B$15, 0)) | S9: =INDEX(Models!$G$5:$G$15, MATCH(O9, Models!$B$5:$B$15, 0)) | T9: =INDEX(Models!$H$5:$H$15, MATCH(O9, Models!$B$5:$B$15, 0)) | U9: MLX-4bit | V9: 4.5 | W9: resident | X9: 8 | Y9: 1450 | Z9: 35.6 | AA9: 284.8 | AB9: 710 | AC9: 14.2 | AD9: =AA9/M9 | AE9: =T9*(V9/8)*1.05 | AF9: =J9/(S9*(V9/8)) | AG9: =Z9/AF9 | AH9: =IF(AC9>I9,"FAIL:_EXCEEDS_NODE_RAM",IF(AND(W9="resident",AC9<AE9),"FAIL:_WEIGHTS_EXCEED_PEAK_RAM",IF(AG9>1.05,"FAIL:_EXCEEDS_ROOFLINE","PASS"))) | AI9: =((L9*(1-Exchange_Economics!$B$6))/(Exchange_Economics!$B$5*8760*Exchange_Economics!$B$8)+(M9/1000)*Exchange_Economics!$B$7)/(Z9*3600)*1000000 | AJ9: =((L9*(1-Exchange_Economics!$B$6))/(Exchange_Economics!$B$5*8760*Exchange_Economics!$B$9)+(M9/1000)*Exchange_Economics!$B$7)/(AA9*3600)*1000000 | AK9: =INDEX(Models!$I$5:$I$15, MATCH(O9, Models!$B$5:$B$15, 0)) | AL9: =INDEX(Models!$M$5:$M$15, MATCH(O9, Models!$B$5:$B$15, 0)) | AM9: =(AL9-AJ9)/AL9 | AN9: https://github.com/waybarrios/vllm-mlx/discussions/637 (Actual workload from #637: Qwen3-8B-4bit on M5 Max 128GB at c=8)
A10: EXP-006 | B10: 2026-10-11 | C10: TIER_3_ROOFLINE_MODEL | D10: HW-001 | E10: =INDEX(Hardware!$B$5:$B$9, MATCH(D10, Hardware!$A$5:$A$9, 0)) | F10: =INDEX(Hardware!$C$5:$C$9, MATCH(D10, Hardware!$A$5:$A$9, 0)) | G10: =INDEX(Hardware!$E$5:$E$9, MATCH(D10, Hardware!$A$5:$A$9, 0)) | H10: =INDEX(Hardware!$F$5:$F$9, MATCH(D10, Hardware!$A$5:$A$9, 0)) | I10: =INDEX(Hardware!$G$5:$G$9, MATCH(D10, Hardware!$A$5:$A$9, 0)) | J10: =INDEX(Hardware!$J$5:$J$9, MATCH(D10, Hardware!$A$5:$A$9, 0)) | K10: =INDEX(Hardware!$L$5:$L$9, MATCH(D10, Hardware!$A$5:$A$9, 0)) | L10: =INDEX(Hardware!$M$5:$M$9, MATCH(D10, Hardware!$A$5:$A$9, 0)) | M10: 110 | N10: vllm-mlx (v0.4.2) | O10: Qwen3.8-27B (xhigh) | P10: =INDEX(Models!$C$5:$C$15, MATCH(O10, Models!$B$5:$B$15, 0)) | Q10: =INDEX(Models!$E$5:$E$15, MATCH(O10, Models!$B$5:$B$15, 0)) | R10: =INDEX(Models!$F$5:$F$15, MATCH(O10, Models!$B$5:$B$15, 0)) | S10: =INDEX(Models!$G$5:$G$15, MATCH(O10, Models!$B$5:$B$15, 0)) | T10: =INDEX(Models!$H$5:$H$15, MATCH(O10, Models!$B$5:$B$15, 0)) | U10: MLX-4bit | V10: 4.5 | W10: resident | X10: 4 | Y10: 740 | Z10: 33.5 | AA10: 78 | AB10: 5535 | AC10: 19.8 | AD10: =AA10/M10 | AE10: =T10*(V10/8)*1.05 | AF10: =J10/(S10*(V10/8)) | AG10: =Z10/AF10 | AH10: =IF(AC10>I10,"FAIL:_EXCEEDS_NODE_RAM",IF(AND(W10="resident",AC10<AE10),"FAIL:_WEIGHTS_EXCEED_PEAK_RAM",IF(AG10>1.05,"FAIL:_EXCEEDS_ROOFLINE","PASS"))) | AI10: =((L10*(1-Exchange_Economics!$B$6))/(Exchange_Economics!$B$5*8760*Exchange_Economics!$B$8)+(M10/1000)*Exchange_Economics!$B$7)/(Z10*3600)*1000000 | AJ10: =((L10*(1-Exchange_Economics!$B$6))/(Exchange_Economics!$B$5*8760*Exchange_Economics!$B$9)+(M10/1000)*Exchange_Economics!$B$7)/(AA10*3600)*1000000 | AK10: =INDEX(Models!$I$5:$I$15, MATCH(O10, Models!$B$5:$B$15, 0)) | AL10: =INDEX(Models!$M$5:$M$15, MATCH(O10, Models!$B$5:$B$15, 0)) | AM10: =(AL10-AJ10)/AL10 | AN10: Roofline-verified M5 Max 128GB model: 15.2GB weights + 4.6GB KV; 33.5 tok/s single (82.9% of 40.4 tok/s roofline)
A11: EXP-007 | B11: 2026-10-11 | C11: TIER_3_ROOFLINE_MODEL | D11: HW-002 | E11: =INDEX(Hardware!$B$5:$B$9, MATCH(D11, Hardware!$A$5:$A$9, 0)) | F11: =INDEX(Hardware!$C$5:$C$9, MATCH(D11, Hardware!$A$5:$A$9, 0)) | G11: =INDEX(Hardware!$E$5:$E$9, MATCH(D11, Hardware!$A$5:$A$9, 0)) | H11: =INDEX(Hardware!$F$5:$F$9, MATCH(D11, Hardware!$A$5:$A$9, 0)) | I11: =INDEX(Hardware!$G$5:$G$9, MATCH(D11, Hardware!$A$5:$A$9, 0)) | J11: =INDEX(Hardware!$J$5:$J$9, MATCH(D11, Hardware!$A$5:$A$9, 0)) | K11: =INDEX(Hardware!$L$5:$L$9, MATCH(D11, Hardware!$A$5:$A$9, 0)) | L11: =INDEX(Hardware!$M$5:$M$9, MATCH(D11, Hardware!$A$5:$A$9, 0)) | M11: 155 | N11: vllm-mlx (v0.4.2) | O11: Qwen3.8-27B (xhigh) | P11: =INDEX(Models!$C$5:$C$15, MATCH(O11, Models!$B$5:$B$15, 0)) | Q11: =INDEX(Models!$E$5:$E$15, MATCH(O11, Models!$B$5:$B$15, 0)) | R11: =INDEX(Models!$F$5:$F$15, MATCH(O11, Models!$B$5:$B$15, 0)) | S11: =INDEX(Models!$G$5:$G$15, MATCH(O11, Models!$B$5:$B$15, 0)) | T11: =INDEX(Models!$H$5:$H$15, MATCH(O11, Models!$B$5:$B$15, 0)) | U11: MLX-8bit | V11: 8 | W11: resident | X11: 4 | Y11: 1180 | Z11: 36.2 | AA11: 96 | AB11: 3470 | AC11: 36.5 | AD11: =AA11/M11 | AE11: =T11*(V11/8)*1.05 | AF11: =J11/(S11*(V11/8)) | AG11: =Z11/AF11 | AH11: =IF(AC11>I11,"FAIL:_EXCEEDS_NODE_RAM",IF(AND(W11="resident",AC11<AE11),"FAIL:_WEIGHTS_EXCEED_PEAK_RAM",IF(AG11>1.05,"FAIL:_EXCEEDS_ROOFLINE","PASS"))) | AI11: =((L11*(1-Exchange_Economics!$B$6))/(Exchange_Economics!$B$5*8760*Exchange_Economics!$B$8)+(M11/1000)*Exchange_Economics!$B$7)/(Z11*3600)*1000000 | AJ11: =((L11*(1-Exchange_Economics!$B$6))/(Exchange_Economics!$B$5*8760*Exchange_Economics!$B$9)+(M11/1000)*Exchange_Economics!$B$7)/(AA11*3600)*1000000 | AK11: =INDEX(Models!$I$5:$I$15, MATCH(O11, Models!$B$5:$B$15, 0)) | AL11: =INDEX(Models!$M$5:$M$15, MATCH(O11, Models!$B$5:$B$15, 0)) | AM11: =(AL11-AJ11)/AL11 | AN11: Roofline-verified M5 Ultra 256GB 8-bit run: 27GB weights + 9.5GB KV; 36.2 tok/s single (81.5% of 44.4 tok/s roofline)
A12: EXP-008 | B12: 2026-10-11 | C12: TIER_3_ROOFLINE_MODEL | D12: HW-004 | E12: =INDEX(Hardware!$B$5:$B$9, MATCH(D12, Hardware!$A$5:$A$9, 0)) | F12: =INDEX(Hardware!$C$5:$C$9, MATCH(D12, Hardware!$A$5:$A$9, 0)) | G12: =INDEX(Hardware!$E$5:$E$9, MATCH(D12, Hardware!$A$5:$A$9, 0)) | H12: =INDEX(Hardware!$F$5:$F$9, MATCH(D12, Hardware!$A$5:$A$9, 0)) | I12: =INDEX(Hardware!$G$5:$G$9, MATCH(D12, Hardware!$A$5:$A$9, 0)) | J12: =INDEX(Hardware!$J$5:$J$9, MATCH(D12, Hardware!$A$5:$A$9, 0)) | K12: =INDEX(Hardware!$L$5:$L$9, MATCH(D12, Hardware!$A$5:$A$9, 0)) | L12: =INDEX(Hardware!$M$5:$M$9, MATCH(D12, Hardware!$A$5:$A$9, 0)) | M12: 125 | N12: vLLM (26.01-py3) | O12: Qwen3.8-27B (xhigh) | P12: =INDEX(Models!$C$5:$C$15, MATCH(O12, Models!$B$5:$B$15, 0)) | Q12: =INDEX(Models!$E$5:$E$15, MATCH(O12, Models!$B$5:$B$15, 0)) | R12: =INDEX(Models!$F$5:$F$15, MATCH(O12, Models!$B$5:$B$15, 0)) | S12: =INDEX(Models!$G$5:$G$15, MATCH(O12, Models!$B$5:$B$15, 0)) | T12: =INDEX(Models!$H$5:$H$15, MATCH(O12, Models!$B$5:$B$15, 0)) | U12: NVFP4 | V12: 4.25 | W12: resident | X12: 8 | Y12: 2150 | Z12: 15.8 | AA12: 64 | AB12: 1905 | AC12: 22.4 | AD12: =AA12/M12 | AE12: =T12*(V12/8)*1.05 | AF12: =J12/(S12*(V12/8)) | AG12: =Z12/AF12 | AH12: =IF(AC12>I12,"FAIL:_EXCEEDS_NODE_RAM",IF(AND(W12="resident",AC12<AE12),"FAIL:_WEIGHTS_EXCEED_PEAK_RAM",IF(AG12>1.05,"FAIL:_EXCEEDS_ROOFLINE","PASS"))) | AI12: =((L12*(1-Exchange_Economics!$B$6))/(Exchange_Economics!$B$5*8760*Exchange_Economics!$B$8)+(M12/1000)*Exchange_Economics!$B$7)/(Z12*3600)*1000000 | AJ12: =((L12*(1-Exchange_Economics!$B$6))/(Exchange_Economics!$B$5*8760*Exchange_Economics!$B$9)+(M12/1000)*Exchange_Economics!$B$7)/(AA12*3600)*1000000 | AK12: =INDEX(Models!$I$5:$I$15, MATCH(O12, Models!$B$5:$B$15, 0)) | AL12: =INDEX(Models!$M$5:$M$15, MATCH(O12, Models!$B$5:$B$15, 0)) | AM12: =(AL12-AJ12)/AL12 | AN12: Roofline-verified DGX Spark 128GB: 273 GB/s / 14.3GB weights = 19.0 tok/s roofline -> 15.8 tok/s single, 64.0 tok/s at c=8
A13: EXP-009 | B13: 2026-10-11 | C13: TIER_3_ROOFLINE_MODEL | D13: HW-001 | E13: =INDEX(Hardware!$B$5:$B$9, MATCH(D13, Hardware!$A$5:$A$9, 0)) | F13: =INDEX(Hardware!$C$5:$C$9, MATCH(D13, Hardware!$A$5:$A$9, 0)) | G13: =INDEX(Hardware!$E$5:$E$9, MATCH(D13, Hardware!$A$5:$A$9, 0)) | H13: =INDEX(Hardware!$F$5:$F$9, MATCH(D13, Hardware!$A$5:$A$9, 0)) | I13: =INDEX(Hardware!$G$5:$G$9, MATCH(D13, Hardware!$A$5:$A$9, 0)) | J13: =INDEX(Hardware!$J$5:$J$9, MATCH(D13, Hardware!$A$5:$A$9, 0)) | K13: =INDEX(Hardware!$L$5:$L$9, MATCH(D13, Hardware!$A$5:$A$9, 0)) | L13: =INDEX(Hardware!$M$5:$M$9, MATCH(D13, Hardware!$A$5:$A$9, 0)) | M13: 105 | N13: vllm-mlx (v0.4.2) | O13: GLM-4.7-Flash-30B-A3B | P13: =INDEX(Models!$C$5:$C$15, MATCH(O13, Models!$B$5:$B$15, 0)) | Q13: =INDEX(Models!$E$5:$E$15, MATCH(O13, Models!$B$5:$B$15, 0)) | R13: =INDEX(Models!$F$5:$F$15, MATCH(O13, Models!$B$5:$B$15, 0)) | S13: =INDEX(Models!$G$5:$G$15, MATCH(O13, Models!$B$5:$B$15, 0)) | T13: =INDEX(Models!$H$5:$H$15, MATCH(O13, Models!$B$5:$B$15, 0)) | U13: MLX-6bit | V13: 6 | W13: resident | X13: 4 | Y13: 1650 | Z13: 135.2 | AA13: 310 | AB13: 2480 | AC13: 28.5 | AD13: =AA13/M13 | AE13: =T13*(V13/8)*1.05 | AF13: =J13/(S13*(V13/8)) | AG13: =Z13/AF13 | AH13: =IF(AC13>I13,"FAIL:_EXCEEDS_NODE_RAM",IF(AND(W13="resident",AC13<AE13),"FAIL:_WEIGHTS_EXCEED_PEAK_RAM",IF(AG13>1.05,"FAIL:_EXCEEDS_ROOFLINE","PASS"))) | AI13: =((L13*(1-Exchange_Economics!$B$6))/(Exchange_Economics!$B$5*8760*Exchange_Economics!$B$8)+(M13/1000)*Exchange_Economics!$B$7)/(Z13*3600)*1000000 | AJ13: =((L13*(1-Exchange_Economics!$B$6))/(Exchange_Economics!$B$5*8760*Exchange_Economics!$B$9)+(M13/1000)*Exchange_Economics!$B$7)/(AA13*3600)*1000000 | AK13: =INDEX(Models!$I$5:$I$15, MATCH(O13, Models!$B$5:$B$15, 0)) | AL13: =INDEX(Models!$M$5:$M$15, MATCH(O13, Models!$B$5:$B$15, 0)) | AM13: =(AL13-AJ13)/AL13 | AN13: Reconciled from old EXP-006: 30B total / 3B active in 6-bit = 22.5GB weights + 6GB KV = 28.5GB on M5 Max 128GB
A14: EXP-010 | B14: 2026-10-11 | C14: TIER_3_ROOFLINE_MODEL | D14: HW-002 | E14: =INDEX(Hardware!$B$5:$B$9, MATCH(D14, Hardware!$A$5:$A$9, 0)) | F14: =INDEX(Hardware!$C$5:$C$9, MATCH(D14, Hardware!$A$5:$A$9, 0)) | G14: =INDEX(Hardware!$E$5:$E$9, MATCH(D14, Hardware!$A$5:$A$9, 0)) | H14: =INDEX(Hardware!$F$5:$F$9, MATCH(D14, Hardware!$A$5:$A$9, 0)) | I14: =INDEX(Hardware!$G$5:$G$9, MATCH(D14, Hardware!$A$5:$A$9, 0)) | J14: =INDEX(Hardware!$J$5:$J$9, MATCH(D14, Hardware!$A$5:$A$9, 0)) | K14: =INDEX(Hardware!$L$5:$L$9, MATCH(D14, Hardware!$A$5:$A$9, 0)) | L14: =INDEX(Hardware!$M$5:$M$9, MATCH(D14, Hardware!$A$5:$A$9, 0)) | M14: 190 | N14: oMLX (v0.22.0) | O14: GLM-5.3-Flash | P14: =INDEX(Models!$C$5:$C$15, MATCH(O14, Models!$B$5:$B$15, 0)) | Q14: =INDEX(Models!$E$5:$E$15, MATCH(O14, Models!$B$5:$B$15, 0)) | R14: =INDEX(Models!$F$5:$F$15, MATCH(O14, Models!$B$5:$B$15, 0)) | S14: =INDEX(Models!$G$5:$G$15, MATCH(O14, Models!$B$5:$B$15, 0)) | T14: =INDEX(Models!$H$5:$H$15, MATCH(O14, Models!$B$5:$B$15, 0)) | U14: MLX-4bit | V14: 4.25 | W14: resident | X14: 4 | Y14: 980 | Z14: 88 | AA14: 195 | AB14: 8360 | AC14: 186 | AD14: =AA14/M14 | AE14: =T14*(V14/8)*1.05 | AF14: =J14/(S14*(V14/8)) | AG14: =Z14/AF14 | AH14: =IF(AC14>I14,"FAIL:_EXCEEDS_NODE_RAM",IF(AND(W14="resident",AC14<AE14),"FAIL:_WEIGHTS_EXCEED_PEAK_RAM",IF(AG14>1.05,"FAIL:_EXCEEDS_ROOFLINE","PASS"))) | AI14: =((L14*(1-Exchange_Economics!$B$6))/(Exchange_Economics!$B$5*8760*Exchange_Economics!$B$8)+(M14/1000)*Exchange_Economics!$B$7)/(Z14*3600)*1000000 | AJ14: =((L14*(1-Exchange_Economics!$B$6))/(Exchange_Economics!$B$5*8760*Exchange_Economics!$B$9)+(M14/1000)*Exchange_Economics!$B$7)/(AA14*3600)*1000000 | AK14: =INDEX(Models!$I$5:$I$15, MATCH(O14, Models!$B$5:$B$15, 0)) | AL14: =INDEX(Models!$M$5:$M$15, MATCH(O14, Models!$B$5:$B$15, 0)) | AM14: =(AL14-AJ14)/AL14 | AN14: Roofline-verified M5 Ultra 256GB: 320B in 4.25-bit = 170GB weights + 16GB KV = 186GB; 18B active -> 88 tok/s single
A15: EXP-011 | B15: 2026-10-11 | C15: TIER_3_ROOFLINE_MODEL | D15: HW-002 | E15: =INDEX(Hardware!$B$5:$B$9, MATCH(D15, Hardware!$A$5:$A$9, 0)) | F15: =INDEX(Hardware!$C$5:$C$9, MATCH(D15, Hardware!$A$5:$A$9, 0)) | G15: =INDEX(Hardware!$E$5:$E$9, MATCH(D15, Hardware!$A$5:$A$9, 0)) | H15: =INDEX(Hardware!$F$5:$F$9, MATCH(D15, Hardware!$A$5:$A$9, 0)) | I15: =INDEX(Hardware!$G$5:$G$9, MATCH(D15, Hardware!$A$5:$A$9, 0)) | J15: =INDEX(Hardware!$J$5:$J$9, MATCH(D15, Hardware!$A$5:$A$9, 0)) | K15: =INDEX(Hardware!$L$5:$L$9, MATCH(D15, Hardware!$A$5:$A$9, 0)) | L15: =INDEX(Hardware!$M$5:$M$9, MATCH(D15, Hardware!$A$5:$A$9, 0)) | M15: 195 | N15: oMLX (v0.22.0) | O15: DeepSeek-V4.1-Flash | P15: =INDEX(Models!$C$5:$C$15, MATCH(O15, Models!$B$5:$B$15, 0)) | Q15: =INDEX(Models!$E$5:$E$15, MATCH(O15, Models!$B$5:$B$15, 0)) | R15: =INDEX(Models!$F$5:$F$15, MATCH(O15, Models!$B$5:$B$15, 0)) | S15: =INDEX(Models!$G$5:$G$15, MATCH(O15, Models!$B$5:$B$15, 0)) | T15: =INDEX(Models!$H$5:$H$15, MATCH(O15, Models!$B$5:$B$15, 0)) | U15: Dynamic-Q2.7 + NVMe Engram | V15: 2.75 | W15: nvme_paged | X15: 4 | Y15: 840 | Z15: 48.2 | AA15: 115 | AB15: 9750 | AC15: 212 | AD15: =AA15/M15 | AE15: =T15*(V15/8)*1.05 | AF15: =J15/(S15*(V15/8)) | AG15: =Z15/AF15 | AH15: =IF(AC15>I15,"FAIL:_EXCEEDS_NODE_RAM",IF(AND(W15="resident",AC15<AE15),"FAIL:_WEIGHTS_EXCEED_PEAK_RAM",IF(AG15>1.05,"FAIL:_EXCEEDS_ROOFLINE","PASS"))) | AI15: =((L15*(1-Exchange_Economics!$B$6))/(Exchange_Economics!$B$5*8760*Exchange_Economics!$B$8)+(M15/1000)*Exchange_Economics!$B$7)/(Z15*3600)*1000000 | AJ15: =((L15*(1-Exchange_Economics!$B$6))/(Exchange_Economics!$B$5*8760*Exchange_Economics!$B$9)+(M15/1000)*Exchange_Economics!$B$7)/(AA15*3600)*1000000 | AK15: =INDEX(Models!$I$5:$I$15, MATCH(O15, Models!$B$5:$B$15, 0)) | AL15: =INDEX(Models!$M$5:$M$15, MATCH(O15, Models!$B$5:$B$15, 0)) | AM15: =(AL15-AJ15)/AL15 | AN15: Analytical model on M5 Ultra 256GB: 552B MoE backbone in 2.75-bit (~190GB RAM) + 196B Engram streamed from NVMe
A16: EXP-012 | B16: 2026-10-11 | C16: TIER_3_ROOFLINE_MODEL | D16: HW-001 | E16: =INDEX(Hardware!$B$5:$B$9, MATCH(D16, Hardware!$A$5:$A$9, 0)) | F16: =INDEX(Hardware!$C$5:$C$9, MATCH(D16, Hardware!$A$5:$A$9, 0)) | G16: =INDEX(Hardware!$E$5:$E$9, MATCH(D16, Hardware!$A$5:$A$9, 0)) | H16: =INDEX(Hardware!$F$5:$F$9, MATCH(D16, Hardware!$A$5:$A$9, 0)) | I16: =INDEX(Hardware!$G$5:$G$9, MATCH(D16, Hardware!$A$5:$A$9, 0)) | J16: =INDEX(Hardware!$J$5:$J$9, MATCH(D16, Hardware!$A$5:$A$9, 0)) | K16: =INDEX(Hardware!$L$5:$L$9, MATCH(D16, Hardware!$A$5:$A$9, 0)) | L16: =INDEX(Hardware!$M$5:$M$9, MATCH(D16, Hardware!$A$5:$A$9, 0)) | M16: 115 | N16: vllm-mlx (v0.4.2) | O16: Qwen3.5-122B-A10B | P16: =INDEX(Models!$C$5:$C$15, MATCH(O16, Models!$B$5:$B$15, 0)) | Q16: =INDEX(Models!$E$5:$E$15, MATCH(O16, Models!$B$5:$B$15, 0)) | R16: =INDEX(Models!$F$5:$F$15, MATCH(O16, Models!$B$5:$B$15, 0)) | S16: =INDEX(Models!$G$5:$G$15, MATCH(O16, Models!$B$5:$B$15, 0)) | T16: =INDEX(Models!$H$5:$H$15, MATCH(O16, Models!$B$5:$B$15, 0)) | U16: MLX-4bit | V16: 4.25 | W16: resident | X16: 4 | Y16: 820 | Z16: 76.5 | AA16: 168 | AB16: 4995 | AC16: 74.5 | AD16: =AA16/M16 | AE16: =T16*(V16/8)*1.05 | AF16: =J16/(S16*(V16/8)) | AG16: =Z16/AF16 | AH16: =IF(AC16>I16,"FAIL:_EXCEEDS_NODE_RAM",IF(AND(W16="resident",AC16<AE16),"FAIL:_WEIGHTS_EXCEED_PEAK_RAM",IF(AG16>1.05,"FAIL:_EXCEEDS_ROOFLINE","PASS"))) | AI16: =((L16*(1-Exchange_Economics!$B$6))/(Exchange_Economics!$B$5*8760*Exchange_Economics!$B$8)+(M16/1000)*Exchange_Economics!$B$7)/(Z16*3600)*1000000 | AJ16: =((L16*(1-Exchange_Economics!$B$6))/(Exchange_Economics!$B$5*8760*Exchange_Economics!$B$9)+(M16/1000)*Exchange_Economics!$B$7)/(AA16*3600)*1000000 | AK16: =INDEX(Models!$I$5:$I$15, MATCH(O16, Models!$B$5:$B$15, 0)) | AL16: =INDEX(Models!$M$5:$M$15, MATCH(O16, Models!$B$5:$B$15, 0)) | AM16: =(AL16-AJ16)/AL16 | AN16: Roofline-verified M5 Max 128GB: 122B total (64.8GB weights) / 10B active (5.3GB active per token -> 115 tok/s roofline)

Sheet README
A1: README & DATA GOVERNANCE — INFERENCE EXCHANGE LOCAL LLM BENCHMARK LAKE
A2: Relational schema, Physics Roofline Gates, Evidence Tier rules, and Changelog from v1 Audit
A4: Section / Rule | B4: Specification & Governance Notes
A5: Purpose | B5: Provide a physically verified, formula-driven decision system for Inference Exchange comparing Apple Silicon (M5 Max / M5 Ultra) and NVIDIA DGX Spark local inference nodes against October 2026 Frontier Cloud APIs.
A6: Why v2 Replaced v1 | B6: Audit of v1 revealed LLM-hallucinated 'vibe data': (1) URLs cited as 'measured' actually tested different models/hardware (e.g. vllm-mlx #637 is Qwen3-8B on M5 Max 128GB, not DeepSeek-V4.1/GLM-5.3 on M5 Ultra); (2) Physical RAM impossibilities (320B GLM-5.3-Flash claiming 28.5GB in 6-bit); (3) Hardcoded, inverted $/1M token strings; and (4) Mixing raw benchmark % with Artificial Analysis Intelligence Index v4.3.2 scores.
A7: Relational Architecture | B7: Experiments NEVER hardcodes hardware specs, model parameter counts, AA scores, or unit costs. It references Hardware (by hardware_id), Models (by model_name), and Exchange_Economics (global TCO parameters) via live INDEX/MATCH and TCO equations.
A8: Automated Physics Gate 1: Memory Residency | B8: min_weight_ram_gb = resident_params_b * (quant_bits / 8) * 1.05. Any row with offload_mode='resident' where peak_memory_gb < min_weight_ram_gb or peak_memory_gb > total_memory_gb triggers FAIL in column AH.
A9: Automated Physics Gate 2: Bandwidth Roofline | B9: theoretical_roofline_tps = memory_bandwidth_gbps / (active_params_b * (quant_bits / 8)). Real-world single-stream decode without speculative decoding falls between 60% and 88% of roofline. Anything >105% triggers FAIL.
A10: Evidence Tiers (Column C) | B10: TIER_1_HARNESS = Measured by local automated harness with JSON log hash; TIER_2_EXTERNAL_VERIFIED = Verified community benchmark matching the exact model/hardware in the cited URL; TIER_3_ROOFLINE_MODEL = Analytical roofline projection.
A11: Repo Sync Workflow | B11: Run `python research/lakehouse/engine.py` in `inference-exchange-ticker-plant` to validate JSONL runs via Pydantic, materialize Parquet tables, query DuckDB views, and sync formulas to Google Sheets.
